evolvishub_sqlite_adapter/__init__.py
evolvishub_sqlite_adapter/config.py
evolvishub_sqlite_adapter/dataframe_adapter.py
evolvishub_sqlite_adapter/async_adapter/__init__.py
evolvishub_sqlite_adapter/async_adapter/adapter.py
evolvishub_sqlite_adapter/migrations/__init__.py
evolvishub_sqlite_adapter/migrations/flyway.py
evolvishub_sqlite_adapter/sync/adapter.py
evolvishub_sqlite_adapter/sync_adapter/__init__.py
evolvishub_sqlite_adapter/sync_adapter/adapter.py
evolvishub_sqlite_adapter/utils/__init__.py
evolvishub_sqlite_adapter/utils/exceptions.py
evolvishub_sqlite_adapter/utils/logger.py
evolvishub_sqlite_adapter-0.1.4.dist-info/licenses/LICENSE
evolvishub_sqlite_adapter-0.1.4.dist-info/METADATA
evolvishub_sqlite_adapter-0.1.4.dist-info/WHEEL
evolvishub_sqlite_adapter-0.1.4.dist-info/top_level.txt
evolvishub_sqlite_adapter-0.1.4.dist-info/RECORD
